haze/__init__.py
haze/ec2.py
haze/cli/__init__.py
haze/cli/awsmetadata.py
haze/cli/commands.py
haze/cli/conductor.py
haze-0.1.37.dist-info/DESCRIPTION.rst
haze-0.1.37.dist-info/METADATA
haze-0.1.37.dist-info/RECORD
haze-0.1.37.dist-info/WHEEL
haze-0.1.37.dist-info/entry_points.txt
haze-0.1.37.dist-info/metadata.json
haze-0.1.37.dist-info/top_level.txt
