Metadata-Version: 2.0
Name: haze
Version: 0.1.37
Summary: Haze is a collection of AWS utility functions
Home-page: https://github.com/unixorn/haze
Author: Joe Block
Author-email: jpb@unixorn.net
License: UNKNOWN
Download-URL: https://github.com/unixorn/haze/tarball/0.1.37
Keywords: aws,cloud
Platform: UNKNOWN
Classifier: Development Status :: 3 - Alpha
Classifier: Operating System :: POSIX
Classifier: License :: OSI Approved :: Apache Software License
Classifier: Programming Language :: Python :: 2.7
Classifier: Topic :: System :: Systems Administration
Requires-Dist: boto (>=2.38.0)
Requires-Dist: logrus (>=0.0.2)
